Metadata-Version: 2.1
Name: smsaero_api
Version: 3.1.1
Summary: Python client for working with SMS Aero API.
Home-page: https://github.com/smsaero/smsaero_python/
Download-URL: https://github.com/smsaero/smsaero_python/archive/refs/tags/3.1.0.tar.gz
Author: SMS Aero
Author-email: admin@smsaero.ru
Maintainer: SMS Aero Team
Maintainer-email: support@smsaero.ru
License: MIT
Project-URL: Homepage, https://smsaero.ru/
Project-URL: Repository, https://github.com/smsaero/smsaero_python/
Project-URL: Bug Tracker, https://github.com/smsaero/smsaero_python/issues
Project-URL: Help Center, https://smsaero.ru/support/
Keywords: smsaero,api,smsaero_api,sms,hlr,viber
Platform: any
Classifier: Development Status :: 5 - Production/Stable
Classifier: Environment :: Web Environment
Classifier: Environment :: Console
Classifier: Intended Audience :: Developers
Classifier: Intended Audience :: System Administrators
Classifier: License :: OSI Approved :: MIT License
Classifier: Operating System :: OS Independent
Classifier: Programming Language :: Python
Classifier: Programming Language :: Python :: 3
Classifier: Programming Language :: Python :: 3 :: Only
Classifier: Programming Language :: Python :: 3.6
Classifier: Programming Language :: Python :: 3.7
Classifier: Programming Language :: Python :: 3.8
Classifier: Programming Language :: Python :: 3.9
Classifier: Programming Language :: Python :: 3.10
Classifier: Programming Language :: Python :: 3.11
Classifier: Programming Language :: Python :: 3.12
Classifier: Programming Language :: Python :: 3.13
Classifier: Programming Language :: Python :: 3.14
Classifier: Programming Language :: Python :: Implementation :: CPython
Classifier: Topic :: Software Development :: Libraries :: Python Modules
Classifier: Topic :: Communications :: Telephony
Classifier: Topic :: Internet :: WWW/HTTP
Classifier: Topic :: Software Development :: Libraries :: Python Modules
Requires-Python: >=3.6
License-File: LICENSE
License-File: AUTHORS.md
Requires-Dist: setuptools
Requires-Dist: requests
Requires-Dist: phonenumbers
Requires-Dist: email-validator
Provides-Extra: dev
Requires-Dist: pytest >=8.2.2 ; extra == 'dev'
Requires-Dist: requests >=2.0.0 ; extra == 'dev'
Requires-Dist: types-requests >=2.2.2 ; extra == 'dev'
Requires-Dist: flake8 >=7.1.0 ; extra == 'dev'
Requires-Dist: ruff >=0.4.10 ; extra == 'dev'
Requires-Dist: pylint >=3.2.4 ; extra == 'dev'
Requires-Dist: tox >=4.15.1 ; extra == 'dev'
Requires-Dist: mypy >=1.10.0 ; extra == 'dev'
Requires-Dist: coverage >=7.5.4 ; extra == 'dev'
Requires-Dist: bandit >=1.7.9 ; extra == 'dev'
Requires-Dist: build >=1.2.1 ; extra == 'dev'
Requires-Dist: twine >=5.1.1 ; extra == 'dev'
